{
  "name": "If I Never Wake Again☣︎",
  "username": "@catnip66667",
  "bio": "此账号完全传播负能量请谨慎点击 they/she/pan/称呼随意 可以叫我catnip或者猫草 ☠︎overdose☠︎/消极的/neet/焦虑/抑郁/被害妄想/CPTSD/alt/lip/pac/music♡ 此账号偶尔由小爱代理",
  "location": "netherworld",
  "link": "ngl.link/idc86908",
  "avatar": "avatar/avatar.jpg",
  "banner": "avatar/1500x500.jpg",
  "pinned": "2060382093709119775",
  "bio_entities": {
    "mentions": [
      {
        "end": 125,
        "start": 112,
        "username": "madina__mart"
      }
    ]
  }
}
